botmom/__init__.py
botmom/handlers.py
botmom-0.2.dist-info/METADATA
botmom-0.2.dist-info/WHEEL
botmom-0.2.dist-info/top_level.txt
botmom-0.2.dist-info/RECORD
