Metadata-Version: 2.1
Name: botmom
Version: 0.2
Summary: Easiest and most variable module for creating telegram bots
Home-page: https://github.com/Arsenii22/botmom
Author: Arsenii Misiurenko
Author-email: 2028misyurenko.ad@student.letovo.ru
Project-URL: GitHub, https://github.com/Arsenii22/botmom
Keywords: telegram botmom bots chatbots
Classifier: Programming Language :: Python :: 3.11
Classifier: License :: OSI Approved :: MIT License
Classifier: Operating System :: OS Independent
Requires-Python: >=3.6
Requires-Dist: aiogram >=3.0
Requires-Dist: aiohttp
